mkdocs_bi_directional_links/__init__.py
mkdocs_bi_directional_links/link_processor.py
mkdocs_bi_directional_links/plugin.py
mkdocs_bi_directional_links/search_integration.py
mkdocs_bi_directional_links/utils.py
mkdocs_bi_directional_links-0.1.0.dist-info/METADATA
mkdocs_bi_directional_links-0.1.0.dist-info/WHEEL
mkdocs_bi_directional_links-0.1.0.dist-info/entry_points.txt
mkdocs_bi_directional_links-0.1.0.dist-info/top_level.txt
mkdocs_bi_directional_links-0.1.0.dist-info/RECORD
