Metadata-Version: 2.1
Name: mkdocs-bi-directional-links
Version: 0.1.0
Requires-Dist: mkdocs>=1.0
